argdeco.py
argdeco_JoshGoA-1.2.1.dist-info/LICENSE.txt
argdeco_JoshGoA-1.2.1.dist-info/METADATA
argdeco_JoshGoA-1.2.1.dist-info/WHEEL
argdeco_JoshGoA-1.2.1.dist-info/top_level.txt
argdeco_JoshGoA-1.2.1.dist-info/RECORD
