Metadata-Version: 2.1
Name: argdeco-JoshGoA
Version: 1.2.1
Summary: Unopinionated argparse wrapper
Home-page: https://github.com/JoshGoA/argdeco
Author: JoshGoA
License: MIT
Project-URL: Source, https://github.com/pypa/argdeco
Keywords: argparse wrapt
Platform: UNKNOWN
Classifier: Development Status :: 5 - Production/Stable
Classifier: Environment :: Console
Classifier: Intended Audience :: Developers
Classifier: License :: OSI Approved :: MIT License
Classifier: Natural Language :: Basque
Classifier: Natural Language :: English
Classifier: Natural Language :: Spanish
Classifier: Operating System :: OS Independent
Classifier: Programming Language :: Python :: 3.8
Classifier: Topic :: Documentation
Classifier: Topic :: Software Development :: Libraries :: Python Modules
Requires-Python: >=3.8
Requires-Dist: wrapt
